in2lambda/__init__.py
in2lambda/api/__init__.py
in2lambda/api/part.py
in2lambda/api/question.py
in2lambda/api/set.py
in2lambda/api/visibility_status.py
in2lambda/example_questions.tex
in2lambda/example_solutions.tex
in2lambda/figures/O2_potential.png
in2lambda/figures/activated_complex.png
in2lambda/figures/rocket-momentum.png
in2lambda/filters/PartPartSolSol/__init__.py
in2lambda/filters/PartPartSolSol/example.tex
in2lambda/filters/PartPartSolSol/filter.py
in2lambda/filters/PartSolPartSol/__init__.py
in2lambda/filters/PartSolPartSol/example.tex
in2lambda/filters/PartSolPartSol/filter.py
in2lambda/filters/PartsOneSol/__init__.py
in2lambda/filters/PartsOneSol/example.tex
in2lambda/filters/PartsOneSol/filter.py
in2lambda/filters/PartsSepSol/__init__.py
in2lambda/filters/PartsSepSol/example.tex
in2lambda/filters/PartsSepSol/filter.py
in2lambda/filters/__init__.py
in2lambda/filters/markdown.py
in2lambda/json_convert/__init__.py
in2lambda/json_convert/json_convert.py
in2lambda/json_convert/minimal_template_question.json
in2lambda/json_convert/minimal_template_set.json
in2lambda/katex_convert/__init__.py
in2lambda/katex_convert/delete_list.txt
in2lambda/katex_convert/katex_convert.py
in2lambda/katex_convert/replace_list.txt
in2lambda/main.py
in2lambda/py.typed
in2lambda-1.0.0.dist-info/LICENSE
in2lambda-1.0.0.dist-info/METADATA
in2lambda-1.0.0.dist-info/WHEEL
in2lambda-1.0.0.dist-info/entry_points.txt
in2lambda-1.0.0.dist-info/RECORD
