Metadata-Version: 2.3
Name: in2lambda
Version: 1.0.0
Summary: Converts content ready for import into Lambda Feedback
License: MIT
Requires-Python: >=3.10,<4.0
Classifier: Development Status :: 3 - Alpha
Classifier: License :: OSI Approved :: MIT License
Classifier: Natural Language :: English
Classifier: Operating System :: OS Independent
Classifier: Programming Language :: Python :: 3
Classifier: Programming Language :: Python :: 3.10
Classifier: Programming Language :: Python :: 3.11
Classifier: Programming Language :: Python :: 3.12
Classifier: Programming Language :: Python :: 3.13
Classifier: Programming Language :: Python :: 3 :: Only
Classifier: Typing :: Typed
Requires-Dist: beartype (>=0.17.2,<0.18.0)
Requires-Dist: panflute (>=2.3.1,<3.0.0)
Requires-Dist: requests (<2.32.0)
Requires-Dist: rich-click (>=1.7.4,<2.0.0)
Project-URL: Bug Tracker, https://github.com/lambda-feedback/in2lambda/issues
Project-URL: Documentation, https://lambda-feedback.github.io/in2lambda
Project-URL: Homepage, https://lambda-feedback.github.io/in2lambda
Project-URL: Repository, https://github.com/lambda-feedback/in2lambda
